eegsynth/__init__.py
eegsynth/eegsynth.py
lib/ArtNet.py
lib/DummyRedis.py
lib/EDF.py
lib/EEGsynth.py
lib/FakeRedis.py
lib/FieldTrip.py
lib/FieldTrip_test_client.py
lib/FieldTrip_test_server.py
lib/Redis_test_client.py
lib/RingBuffer.py
lib/ZmqRedis.py
lib/__init__.py
lib/colormap.py
module/__init__.py
module/accelerometer/__init__.py
module/accelerometer/accelerometer.py
module/audio2ft/__init__.py
module/audio2ft/audio2ft.py
module/audiomixer/__init__.py
module/audiomixer/audiomixer.py
module/biochill/biochill.py
module/bitalino2ft/__init__.py
module/bitalino2ft/bitalino2ft.py
module/brainflow2ft/__init__.py
module/brainflow2ft/brainflow2ft.py
module/buffer/__init__.py
module/buffer/buffer.py
module/clockdivider/__init__.py
module/clockdivider/clockdivider.py
module/clockmultiplier/__init__.py
module/clockmultiplier/clockmultiplier.py
module/cogito/__init__.py
module/cogito/cogito.py
module/cogito/gtec2wav.py
module/complexity/__init__.py
module/complexity/complexity.py
module/compressor/__init__.py
module/compressor/compressor.py
module/csp/__init__.py
module/csp/csp.py
module/delaytrigger/__init__.py
module/delaytrigger/delaytrigger.py
module/demodulatetone/__init__.py
module/demodulatetone/demodulatetone.py
module/endorphines/__init__.py
module/endorphines/endorphines.py
module/example/__init__.py
module/example/example.py
module/generateclock/__init__.py
module/generateclock/generateclock.py
module/generatecontrol/__init__.py
module/generatecontrol/generatecontrol.py
module/generatesignal/__init__.py
module/generatesignal/generatesignal.py
module/generatetrigger/__init__.py
module/generatetrigger/generatetrigger.py
module/geomixer/__init__.py
module/geomixer/geomixer.py
module/heartrate/__init__.py
module/heartrate/heartrate.py
module/historycontrol/__init__.py
module/historycontrol/historycontrol.py
module/historysignal/__init__.py
module/historysignal/historysignal.py
module/inputcontrol/__init__.py
module/inputcontrol/inputcontrol.py
eegsynth-0.8.0.dist-info/LICENSE.txt
eegsynth-0.8.0.dist-info/METADATA
eegsynth-0.8.0.dist-info/WHEEL
eegsynth-0.8.0.dist-info/entry_points.txt
eegsynth-0.8.0.dist-info/top_level.txt
eegsynth-0.8.0.dist-info/RECORD
