Metadata-Version: 2.1
Name: eegsynth
Version: 0.8.0
Summary: Converting real-time EEG into sounds, music and visual effects
Author-email: Robert Oostenveld <r.oostenveld@gmail.com>
Project-URL: Homepage, http://www.eegsynth.org
Project-URL: Documentation, https://github.com/eegsynth/eegsynth/blob/master/doc/README.md
Project-URL: Source, https://github.com/eegsynth/eegsynth/
Project-URL: Tracker, https://github.com/eegsynth/eegsynth/issues
Keywords: BCI,ECG,EEG,EMG,EOG,ExG,art,brain,brain-computer interface,music,real-time,sonification,sound
Classifier: Development Status :: 5 - Production/Stable
Classifier: Environment :: Console
Classifier: Intended Audience :: Science/Research
Classifier: License :: OSI Approved :: GNU General Public License v3 (GPLv3)
Classifier: Natural Language :: English
Classifier: Operating System :: OS Independent
Classifier: Operating System :: OS Independent
Classifier: Programming Language :: Python
Classifier: Topic :: Artistic Software
Classifier: Topic :: Multimedia :: Sound/Audio
Classifier: Topic :: Scientific/Engineering :: Human Machine Interfaces
Classifier: Topic :: Scientific/Engineering :: Medical Science Apps.
Requires-Python: >=3.8
License-File: LICENSE.txt
Requires-Dist: bleak
Requires-Dist: colorama
Requires-Dist: configparser
Requires-Dist: fuzzywuzzy[speedup]
Requires-Dist: matplotlib
Requires-Dist: mido
Requires-Dist: nilearn
Requires-Dist: numpy
Requires-Dist: opencv-python
Requires-Dist: paho-mqtt
Requires-Dist: pandas
Requires-Dist: pyaudio
Requires-Dist: pylsl
Requires-Dist: PyQt5
Requires-Dist: pyqtgraph
Requires-Dist: pyserial
Requires-Dist: pyzmq
Requires-Dist: redis
Requires-Dist: scikit-learn
Requires-Dist: scipy
Requires-Dist: termcolor
Requires-Dist: toml
Requires-Dist: wiringpi; platform_machine == "armv7l"
Requires-Dist: pyOSC; python_version < "3.5"
Requires-Dist: python-osc; python_version >= "3.5"
